LICENSE.txt
README.md
setup.py
vibpy/__init__.py
vibpy/optic_clock.py
vibpy/vib_cal.py
vibpy.egg-info/PKG-INFO
vibpy.egg-info/SOURCES.txt
vibpy.egg-info/dependency_links.txt
vibpy.egg-info/top_level.txt