Metadata-Version: 2.1
Name: vibpy
Version: 0.0.2
Summary: Python package for Vibration
Author: ghostxy
Author-email: <ghostxy1987@hotmail.com>
License-File: LICENSE.txt
